boapy-0.1.0.dist-info/METADATA
boapy-0.1.0.dist-info/WHEEL
boapy-0.1.0.dist-info/license_files/LICENSE
boa/__init__.py
boa/__init__.pyi
boa/py.typed
boa/boa.cp310-win_amd64.pyd
boapy-0.1.0.dist-info/RECORD
